clcell/__init__.py
clcell/core.py
clcell/device_api.py
clcell-1.0.1.dist-info/LICENSE
clcell-1.0.1.dist-info/METADATA
clcell-1.0.1.dist-info/WHEEL
clcell-1.0.1.dist-info/top_level.txt
clcell-1.0.1.dist-info/RECORD
