Metadata-Version: 2.1
Name: clcell
Version: 1.0.1
Summary: OpenCL-accelerated cellular automata simulator
Home-page: https://github.com/Foxbud/clcell
Author: Garrett Fairburn
License: MIT
Platform: UNKNOWN
Classifier: Topic :: Scientific/Engineering :: Artificial Life
Classifier: License :: OSI Approved :: MIT License
Classifier: Programming Language :: Python :: 3
Classifier: Operating System :: OS Independent
Classifier: Environment :: Other Environment
Classifier: Intended Audience :: Science/Research
Classifier: Natural Language :: English
Requires-Dist: pyopencl (>=2015.2)
Requires-Dist: numpy
